x10/__init__.py
x10/config.py
x10/errors.py
x10/perpetual/__init__.py
x10/perpetual/accounts.py
x10/perpetual/amounts.py
x10/perpetual/assets.py
x10/perpetual/balances.py
x10/perpetual/bridges.py
x10/perpetual/candles.py
x10/perpetual/clients.py
x10/perpetual/configuration.py
x10/perpetual/fees.py
x10/perpetual/funding_rates.py
x10/perpetual/markets.py
x10/perpetual/order_object.py
x10/perpetual/order_object_settlement.py
x10/perpetual/orderbook.py
x10/perpetual/orderbooks.py
x10/perpetual/orders.py
x10/perpetual/positions.py
x10/perpetual/simple_client/simple_trading_client.py
x10/perpetual/stream_client/__init__.py
x10/perpetual/stream_client/perpetual_stream_connection.py
x10/perpetual/stream_client/stream_client.py
x10/perpetual/trades.py
x10/perpetual/trading_client/__init__.py
x10/perpetual/trading_client/account_module.py
x10/perpetual/trading_client/base_module.py
x10/perpetual/trading_client/info_module.py
x10/perpetual/trading_client/markets_information_module.py
x10/perpetual/trading_client/order_management_module.py
x10/perpetual/trading_client/testnet_module.py
x10/perpetual/trading_client/trading_client.py
x10/perpetual/transfer_object.py
x10/perpetual/transfers.py
x10/perpetual/user_client/__init__.py
x10/perpetual/user_client/l1_signing.py
x10/perpetual/user_client/onboarding.py
x10/perpetual/user_client/user_client.py
x10/perpetual/withdrawal_object.py
x10/perpetual/withdrawals.py
x10/utils/__init__.py
x10/utils/date.py
x10/utils/http.py
x10/utils/log.py
x10/utils/model.py
x10/utils/nonce.py
x10/utils/string.py
x10_python_trading_starknet-0.0.17.dist-info/LICENSE
x10_python_trading_starknet-0.0.17.dist-info/METADATA
x10_python_trading_starknet-0.0.17.dist-info/WHEEL
x10_python_trading_starknet-0.0.17.dist-info/RECORD
