Metadata-Version: 2.1
Name: x10-python-trading-starknet
Version: 0.0.17
Summary: Python client for X10 API
Home-page: https://github.com/x10xchange/python_sdk
Author: X10
Author-email: tech@ex10.org
Requires-Python: >=3.10,<4.0
Classifier: Intended Audience :: Developers
Classifier: Operating System :: OS Independent
Classifier: Programming Language :: Python
Classifier: Programming Language :: Python :: 3
Classifier: Programming Language :: Python :: 3.10
Classifier: Programming Language :: Python :: 3.11
Classifier: Programming Language :: Python :: 3.12
Classifier: Topic :: Software Development :: Libraries :: Python Modules
Requires-Dist: aiohttp (>=3.10.11)
Requires-Dist: eth-account (>=0.12.0)
Requires-Dist: fast-stark-crypto (==0.3.8)
Requires-Dist: pydantic (>=2.9.0)
Requires-Dist: pyyaml (>=6.0.1)
Requires-Dist: sortedcontainers (>=2.4.0)
Requires-Dist: strenum (>=0.4.15,<0.5.0)
Requires-Dist: tenacity (>=9.1.2,<10.0.0)
Requires-Dist: websockets (>=12.0,<14.0)
Project-URL: Documentation, https://api.docs.extended.exchange/
Project-URL: Repository, https://github.com/x10xchange/python_sdk
